{
  "101835386931150": {
    "friendCode": "101835386931150",
    "ign": "Ｈ∀Ｙ∀†Σ",
    "name": "REDACTED",
    "nickname": "Hayate",
    "title": "ラビットホール",
    "avatarImage": "https://maimaidx-eng.com/maimai-mobile/img/Icon/5e36d628037fba47.png",
    "rating": "",
    "rank": "Unranked",
    "trophy": "",
    "age": "https://maimaidx-eng.com/maimai-mobile/img/Icon/5e36d628037fba47.png",
    "motto": "Don\\",
    "joined": "2025",
    "bio": "None",
    "guildId": "",
    "achievements": [],
    "articles": [],
    "passwordHash": "",
    "fingerprint": "",
    "isPublic": true,
    "editKey": "",
    "migratedFrom": "hayate.html",
    "migratedAt": "",
    "createdAt": "",
    "updatedAt": ""
  },
  "101680566000997": {
    "friendCode": "101680566000997",
    "ign": "ＪｅｔｌａｇｇΣ",
    "name": "JET PIzarro",
    "nickname": "Jet",
    "title": "勇者ヒンメルならそうしたってことだよ。",
    "avatarImage": "https://maimaidx-eng.com/maimai-mobile/img/Icon/ae94be3e72e23ab5.png",
    "rating": "9531",
    "rank": "Unranked",
    "trophy": "",
    "age": "https://maimaidx-eng.com/maimai-mobile/img/Icon/ae94be3e72e23ab5.png",
    "motto": "Kapag may tiyaga malay mo may afritada",
    "joined": "2025",
    "bio": "Still a noob",
    "guildId": "",
    "achievements": [],
    "articles": [],
    "passwordHash": "",
    "fingerprint": "",
    "isPublic": true,
    "editKey": "",
    "migratedFrom": "jetlagg.html",
    "migratedAt": "",
    "createdAt": "",
    "updatedAt": ""
  },
  "101827591422566": {
    "friendCode": "101827591422566",
    "ign": "ＪｏｏＲａｔ☆",
    "name": "Joo",
    "nickname": "Joo",
    "title": "★==============Σ(ﾟдﾟ；)",
    "avatarImage": "https://maimaidx-eng.com/maimai-mobile/img/Icon/33bc3f1a0dfe6954.png",
    "rating": "",
    "rank": "Unranked",
    "trophy": "",
    "age": "https://maimaidx-eng.com/maimai-mobile/img/Icon/33bc3f1a0dfe6954.png",
    "motto": "N3v3r G3t 0v3r best chart",
    "joined": "2025",
    "bio": "None",
    "guildId": "",
    "achievements": [],
    "articles": [],
    "passwordHash": "",
    "fingerprint": "",
    "isPublic": true,
    "editKey": "",
    "migratedFrom": "joo.html",
    "migratedAt": "",
    "createdAt": "",
    "updatedAt": ""
  },
  "101736423944970": {
    "friendCode": "101736423944970",
    "ign": "Ｋ！",
    "name": "REDACTED",
    "nickname": "Kim",
    "title": "★==============Σ(ﾟдﾟ；)",
    "avatarImage": "https://maimaidx-eng.com/maimai-mobile/img/Icon/8ed59c0111ca92d6.png",
    "rating": "14172",
    "rank": "Unranked",
    "trophy": "",
    "age": "https://maimaidx-eng.com/maimai-mobile/img/Icon/8ed59c0111ca92d6.png",
    "motto": "Unknown",
    "joined": "2025",
    "bio": "No bio provided",
    "guildId": "",
    "achievements": [],
    "articles": [],
    "passwordHash": "",
    "fingerprint": "",
    "isPublic": true,
    "editKey": "",
    "migratedFrom": "k.html",
    "migratedAt": "",
    "createdAt": "",
    "updatedAt": ""
  },
  "9030371471116": {
    "friendCode": "9030371471116",
    "ign": "ＢＭＣ☆Ｋｕｒｉ",
    "name": "Jan Daniel Villafuerte",
    "nickname": "Jandy",
    "title": "MIKU MIKU BEAAAAM!!",
    "avatarImage": "https://maimaidx-eng.com/maimai-mobile/img/Icon/78cbf389d3a76414.png",
    "rating": "15376",
    "rank": "Unranked",
    "trophy": "",
    "age": "https://maimaidx-eng.com/maimai-mobile/img/Icon/78cbf389d3a76414.png",
    "motto": "Wag na kayo maglaro para walang queue",
    "joined": "2025",
    "bio": "I draw a lot and love to play rhythm games every once in a while. Kain ng kain pero walang laman",
    "guildId": "",
    "achievements": [],
    "articles": [],
    "passwordHash": "",
    "fingerprint": "",
    "isPublic": true,
    "editKey": "",
    "migratedFrom": "kuriyama.html",
    "migratedAt": "",
    "createdAt": "",
    "updatedAt": ""
  },
  "101431363711260": {
    "friendCode": "101431363711260",
    "ign": "ｓｅｔｔｅ",
    "name": "REDACTED",
    "nickname": "sett, sette, ian",
    "title": "・・・－－－・・・",
    "avatarImage": "https://maimaidx-eng.com/maimai-mobile/img/Icon/9ca5362a4761cf74.png",
    "rating": "15101",
    "rank": "Unranked",
    "trophy": "",
    "age": "https://maimaidx-eng.com/maimai-mobile/img/Icon/9ca5362a4761cf74.png",
    "motto": "Basta ung mahalaga ung importante",
    "joined": "2025",
    "bio": "chill lang",
    "guildId": "",
    "achievements": [],
    "articles": [],
    "passwordHash": "",
    "fingerprint": "",
    "isPublic": true,
    "editKey": "",
    "migratedFrom": "sette.html",
    "migratedAt": "",
    "createdAt": "",
    "updatedAt": ""
  }
}